randwire.py
randwire-0.1.5.dist-info/METADATA
randwire-0.1.5.dist-info/WHEEL
randwire-0.1.5.dist-info/entry_points.txt
randwire-0.1.5.dist-info/top_level.txt
randwire-0.1.5.dist-info/RECORD
