Metadata-Version: 2.1
Name: randwire
Version: 0.1.5
Summary: Random Length Antenna Calculator
Home-page: https://github.com/0x9900/randwire/
Author: Fred C. (W6BSD)
Author-email: w6bsd@bsdworld.org
License: BSD
Platform: UNKNOWN
Classifier: Development Status :: 3 - Alpha
Classifier: Intended Audience :: Telecommunications Industry
Classifier: License :: OSI Approved :: BSD License
Classifier: Operating System :: OS Independent
Classifier: Programming Language :: Python
Classifier: Programming Language :: Python :: 3
Classifier: Topic :: Communications :: Ham Radio
Requires-Dist: matplotlib
